<?xml version="1.0" encoding="UTF-8" ?>
<databaseChangeLog
        xmlns:xsi="http://www.w3.org/2001/XMLSchema-instance"
        xmlns="http://www.liquibase.org/xml/ns/dbchangelog"
        xsi:schemaLocation="http://www.liquibase.org/xml/ns/dbchangelog http://www.liquibase.org/xml/ns/dbchangelog/dbchangelog-3.1.xsd">

    <changeSet logicalFilePath="insert-purchase_goods.xml"
               id="insert-purchase_goods.xml" author="denis">
        <insert tableName="purchase_goods">
            <column name="purchase_id" value="1"/>
            <column name="good_id" value="1"/>
        </insert>
        <insert tableName="purchase_goods">
            <column name="purchase_id" value="1"/>
            <column name="good_id" value="2"/>
        </insert>
        <insert tableName="purchase_goods">
            <column name="purchase_id" value="1"/>
            <column name="good_id" value="3"/>
        </insert>
        <insert tableName="purchase_goods">
            <column name="purchase_id" value="2"/>
            <column name="good_id" value="2"/>
        </insert>

        <insert tableName="purchase_goods">
            <column name="purchase_id" value="3"/>
            <column name="good_id" value="3"/>
        </insert>
        <insert tableName="purchase_goods">
            <column name="purchase_id" value="3"/>
            <column name="good_id" value="3"/>
        </insert>
        <insert tableName="purchase_goods">
            <column name="purchase_id" value="3"/>
            <column name="good_id" value="3"/>
        </insert>
        <insert tableName="purchase_goods">
            <column name="purchase_id" value="3"/>
            <column name="good_id" value="3"/>
        </insert>
        <insert tableName="purchase_goods">
            <column name="purchase_id" value="3"/>
            <column name="good_id" value="3"/>
        </insert>

        <insert tableName="purchase_goods">
            <column name="purchase_id" value="4"/>
            <column name="good_id" value="5"/>
        </insert>
        <insert tableName="purchase_goods">
            <column name="purchase_id" value="4"/>
            <column name="good_id" value="5"/>
        </insert>
        <insert tableName="purchase_goods">
            <column name="purchase_id" value="4"/>
            <column name="good_id" value="4"/>
        </insert>

        <insert tableName="purchase_goods">
            <column name="purchase_id" value="5"/>
            <column name="good_id" value="2"/>
        </insert>
        <insert tableName="purchase_goods">
            <column name="purchase_id" value="5"/>
            <column name="good_id" value="5"/>
        </insert>
        <insert tableName="purchase_goods">
            <column name="purchase_id" value="5"/>
            <column name="good_id" value="4"/>
        </insert>
    </changeSet>

</databaseChangeLog>